{
  "year": 2026,
  "month": 4,
  "sourceUrl": "https://www.acea.auto/files/Press_release_car_registrations_April_2026.pdf",
  "data": [
    {
      "marque": "Toutes marques",
      "modele": "Tous modèles",
      "total": 330,
      "energie": "BEV"
    },
    {
      "marque": "Toutes marques",
      "modele": "Tous modèles",
      "total": 486,
      "energie": "PHEV"
    },
    {
      "marque": "Toutes marques",
      "modele": "Tous modèles",
      "total": 3828,
      "energie": "HYBRID"
    },
    {
      "marque": "Toutes marques",
      "modele": "Tous modèles",
      "total": 1016,
      "energie": "DIESEL"
    },
    {
      "marque": "Toutes marques",
      "modele": "Tous modèles",
      "total": 2943,
      "energie": "GASOLINE"
    },
    {
      "marque": "Toutes marques",
      "modele": "Tous modèles",
      "total": 55,
      "energie": "OTHER"
    }
  ]
}