{
  "year": 2013,
  "month": 10,
  "data": [
    {
      "marque": "Toutes marques",
      "modele": "Tous modèles",
      "total": 10143,
      "energie": "GASOLINE"
    },
    {
      "marque": "Toutes marques",
      "modele": "Tous modèles",
      "total": 15604,
      "energie": "DIESEL"
    },
    {
      "marque": "Toutes marques",
      "modele": "Tous modèles",
      "total": 80,
      "energie": "BEV"
    },
    {
      "marque": "Toutes marques",
      "modele": "Tous modèles",
      "total": 549,
      "energie": "HYBRID"
    },
    {
      "marque": "Toutes marques",
      "modele": "Tous modèles",
      "total": 67,
      "energie": "PHEV"
    },
    {
      "marque": "Toutes marques",
      "modele": "Tous modèles",
      "total": 658,
      "energie": "LPG_CNG_OTHER"
    }
  ],
  "region": "SE",
  "type": "all"
}