{
  "year": 2020,
  "month": 5,
  "data": [
    {
      "marque": "Toutes marques",
      "modele": "Tous modèles",
      "total": 7628,
      "energie": "GASOLINE"
    },
    {
      "marque": "Toutes marques",
      "modele": "Tous modèles",
      "total": 4445,
      "energie": "DIESEL"
    },
    {
      "marque": "Toutes marques",
      "modele": "Tous modèles",
      "total": 841,
      "energie": "BEV"
    },
    {
      "marque": "Toutes marques",
      "modele": "Tous modèles",
      "total": 1263,
      "energie": "HYBRID"
    },
    {
      "marque": "Toutes marques",
      "modele": "Tous modèles",
      "total": 2591,
      "energie": "PHEV"
    }
  ],
  "region": "SE",
  "type": "all"
}