{
  "year": 2024,
  "month": 12,
  "data": [
    {
      "marque": "Toutes marques",
      "modele": "Tous modèles",
      "total": 113,
      "energie": "BEV"
    },
    {
      "marque": "Toutes marques",
      "modele": "Tous modèles",
      "total": 28,
      "energie": "PHEV"
    },
    {
      "marque": "Toutes marques",
      "modele": "Tous modèles",
      "total": 81,
      "energie": "HYBRID"
    },
    {
      "marque": "Toutes marques",
      "modele": "Tous modèles",
      "total": 445,
      "energie": "DIESEL"
    },
    {
      "marque": "Toutes marques",
      "modele": "Tous modèles",
      "total": 2064,
      "energie": "GASOLINE"
    },
    {
      "marque": "Toutes marques",
      "modele": "Tous modèles",
      "total": 0,
      "energie": "OTHER"
    }
  ]
}