{
  "year": 2022,
  "month": 11,
  "data": [
    {
      "marque": "ALL",
      "modele": "ALL",
      "total": 20009,
      "energie": "GASOLINE"
    },
    {
      "marque": "ALL",
      "modele": "ALL",
      "total": 17052,
      "energie": "BEV"
    },
    {
      "marque": "ALL",
      "modele": "ALL",
      "total": 245,
      "energie": "OTHER"
    },
    {
      "marque": "ALL",
      "modele": "ALL",
      "total": 396,
      "energie": "DIESEL"
    }
  ],
  "region": "NL",
  "type": "all"
}