{
  "year": 2015,
  "month": 2,
  "data": [
    {
      "marque": "Toutes marques",
      "modele": "Tous modèles",
      "total": 88574,
      "energie": "DIESEL"
    },
    {
      "marque": "Toutes marques",
      "modele": "Tous modèles",
      "total": 56832,
      "energie": "GASOLINE"
    },
    {
      "marque": "Toutes marques",
      "modele": "Tous modèles",
      "total": 154474,
      "energie": "HYBRID"
    },
    {
      "marque": "Toutes marques",
      "modele": "Tous modèles",
      "total": 288,
      "energie": "PHEV"
    },
    {
      "marque": "Toutes marques",
      "modele": "Tous modèles",
      "total": 1121,
      "energie": "BEV"
    },
    {
      "marque": "Toutes marques",
      "modele": "Tous modèles",
      "total": 118,
      "energie": "OTHER"
    }
  ],
  "region": "FR",
  "type": "all"
}