{
  "year": 2017,
  "month": 2,
  "data": [
    {
      "marque": "Toutes marques",
      "modele": "Tous modèles",
      "total": 79225,
      "energie": "DIESEL"
    },
    {
      "marque": "Toutes marques",
      "modele": "Tous modèles",
      "total": 78148,
      "energie": "GASOLINE"
    },
    {
      "marque": "Toutes marques",
      "modele": "Tous modèles",
      "total": 169565,
      "energie": "HYBRID"
    },
    {
      "marque": "Toutes marques",
      "modele": "Tous modèles",
      "total": 566,
      "energie": "PHEV"
    },
    {
      "marque": "Toutes marques",
      "modele": "Tous modèles",
      "total": 2304,
      "energie": "BEV"
    },
    {
      "marque": "Toutes marques",
      "modele": "Tous modèles",
      "total": 57,
      "energie": "LPG_CNG_OTHER"
    }
  ],
  "region": "FR",
  "type": "all"
}