{
  "year": 2021,
  "month": 7,
  "data": [
    {
      "marque": "Toutes marques",
      "modele": "Tous modèles",
      "total": 24671,
      "energie": "DIESEL"
    },
    {
      "marque": "Toutes marques",
      "modele": "Tous modèles",
      "total": 49971,
      "energie": "GASOLINE"
    },
    {
      "marque": "Toutes marques",
      "modele": "Tous modèles",
      "total": 119804,
      "energie": "HYBRID"
    },
    {
      "marque": "Toutes marques",
      "modele": "Tous modèles",
      "total": 10709,
      "energie": "PHEV"
    },
    {
      "marque": "Toutes marques",
      "modele": "Tous modèles",
      "total": 7777,
      "energie": "BEV"
    },
    {
      "marque": "Toutes marques",
      "modele": "Tous modèles",
      "total": 3824,
      "energie": "OTHER"
    }
  ],
  "region": "FR",
  "type": "all"
}