{
  "year": 2024,
  "month": 8,
  "data": [
    {
      "marque": "Toutes marques",
      "modele": "Tous modèles",
      "total": 5761,
      "energie": "DIESEL"
    },
    {
      "marque": "Toutes marques",
      "modele": "Tous modèles",
      "total": 27897,
      "energie": "GASOLINE"
    },
    {
      "marque": "Toutes marques",
      "modele": "Tous modèles",
      "total": 95132,
      "energie": "HYBRID"
    },
    {
      "marque": "Toutes marques",
      "modele": "Tous modèles",
      "total": 6212,
      "energie": "PHEV"
    },
    {
      "marque": "Toutes marques",
      "modele": "Tous modèles",
      "total": 13388,
      "energie": "BEV"
    },
    {
      "marque": "Toutes marques",
      "modele": "Tous modèles",
      "total": 3027,
      "energie": "OTHER"
    }
  ],
  "region": "FR",
  "type": "all"
}